podcust/__init__.py
podcust/cli.py
podcust/platform.py
podcust/podcust.py
podcust/tools.py
podcust/commands/__init__.py
podcust/commands/demo.py
podcust/commands/transmission.py
podcust/demo/Dockerfile
podcust/demo/__init__.py
podcust/demo/custodian.py
podcust/transmission/__init__.py
podcust/transmission/custodian.py
podcust/transmission/service.py
podcust/transmission/transmission-kube-template.yml
podcust/transmission/transmission-pod.service
usr/share/man/man1/podcust.1
podcust-0.1.3.dist-info/AUTHORS.rst
podcust-0.1.3.dist-info/METADATA
podcust-0.1.3.dist-info/WHEEL
podcust-0.1.3.dist-info/entry_points.txt
podcust-0.1.3.dist-info/top_level.txt
podcust-0.1.3.dist-info/RECORD
