Metadata-Version: 2.1
Name: podcust
Version: 0.1.3
Summary: Python utility to handle podman containers within Fedora.
Home-page: https://github.com/Iolaum/podcust
Author: Nikolaos Perrakis
Author-email: nikperrakis@gmail.com
License: Parity Public License v7.0.0
Keywords: podcust
Platform: UNKNOWN
Classifier: Development Status :: 2 - Pre-Alpha
Classifier: Intended Audience :: Developers
Classifier: Natural Language :: English
Classifier: Programming Language :: Python :: 3
Classifier: Programming Language :: Python :: 3.9
Requires-Python: >=3.9
Requires-Dist: Click (>=7.0)
Requires-Dist: beautifulsoup4 (>=4.9.2)
Requires-Dist: requests
Provides-Extra: dev
Requires-Dist: pip (>=20.2) ; extra == 'dev'
Requires-Dist: bump2version (>=1.0) ; extra == 'dev'
Requires-Dist: wheel (>=0.35.1) ; extra == 'dev'
Requires-Dist: Sphinx (>=3.2.1) ; extra == 'dev'
Requires-Dist: twine (>=3.2.0) ; extra == 'dev'
Requires-Dist: check-manifest ; extra == 'dev'
Requires-Dist: pytest ; extra == 'dev'
Requires-Dist: pytest-runner ; extra == 'dev'
Requires-Dist: mock ; extra == 'dev'
Requires-Dist: flake8 ; extra == 'dev'
Requires-Dist: black ; extra == 'dev'
Requires-Dist: mypy ; extra == 'dev'
Requires-Dist: tox ; extra == 'dev'
Requires-Dist: coverage ; extra == 'dev'
Requires-Dist: yamllint ; extra == 'dev'
Requires-Dist: doc8 ; extra == 'dev'
